visco/__init__.py
visco/compress_ms.py
visco/decompress_ms.py
visco/main.py
visco/ms_corr_types.yaml
visco/ms_corr_types_reverse.yaml
visco/parser_config/__init__.py
visco/parser_config/compressms.py
visco/parser_config/compressms.yaml
visco/parser_config/decompressms.py
visco/parser_config/decompressms.yaml
visco/schemas/schema_compressms.yaml
visco/schemas/schema_decompression.yaml
visco/utilities.py
visco-0.1.9.dist-info/METADATA
visco-0.1.9.dist-info/WHEEL
visco-0.1.9.dist-info/entry_points.txt
visco-0.1.9.dist-info/RECORD
