Metadata-Version: 2.4
Name: visco
Version: 0.1.9
Summary: A tool for compressing visibility data using singular value decomposition (SVD)
License: GNU GPL v3
Author: Mukundi Ramanyimi
Author-email: rams.muks@gmail.com
Requires-Python: >=3.10,<3.13
Classifier: License :: Other/Proprietary License
Classifier: Programming Language :: Python :: 3
Classifier: Programming Language :: Python :: 3.10
Classifier: Programming Language :: Python :: 3.11
Classifier: Programming Language :: Python :: 3.12
Requires-Dist: click (>=8.1.7,<9.0.0)
Requires-Dist: dask (<2024.11.0)
Requires-Dist: dask-ms[xarray] (>=0.2.21,<0.3.0)
Requires-Dist: distributed (<2024.11.0)
Requires-Dist: numcodecs (<0.16)
Requires-Dist: omegaconf (>=2.3.0,<3.0.0)
Requires-Dist: scipy (>=1.15,<1.16)
Requires-Dist: stimela (>=2.0)
Requires-Dist: tdqm
Requires-Dist: zarr (==2.18.3)
Project-URL: Documentation, https://visco.readthedocs.io
